lungs/__init__.py
lungs/i3d.py
lungs/inflate.py
lungs/main.py
lungs/preprocess.py
lungs/utils.py
lungs-0.1.5.dist-info/LICENSE
lungs-0.1.5.dist-info/METADATA
lungs-0.1.5.dist-info/WHEEL
lungs-0.1.5.dist-info/top_level.txt
lungs-0.1.5.dist-info/RECORD
