Metadata-Version: 2.1
Name: lungs
Version: 0.1.5
Summary: 3D Neural Network for Lung Cancer Risk Prediction on CT Volumes
Home-page: https://github.com/danielkorat/Lung-Cancer-Risk-Prediction
Author: Daniel Korat
Author-email: dkorat@gmail.com
License: UNKNOWN
Platform: UNKNOWN
Classifier: Programming Language :: Python :: 3
Classifier: License :: OSI Approved :: GNU General Public License v3 (GPLv3)
Classifier: Operating System :: OS Independent
Requires-Python: >=3.6
Requires-Dist: tensorflow-gpu (==1.14.0)
Requires-Dist: tensorflow-probability (==0.7.0)
Requires-Dist: dm-sonnet (==1.34)
Requires-Dist: tqdm
Requires-Dist: scipy (==1.4.1)
Requires-Dist: pydicom (==1.4.2)
Requires-Dist: scikit-learn (==0.23.1)
Requires-Dist: scikit-image (==0.16.2)
Requires-Dist: matplotlib
Requires-Dist: scikit-plot (==0.3.7)
Requires-Dist: seaborn (==0.10.1)
Requires-Dist: gdown (==3.11.1)
